odoo/addons/account_invoice_show_currency_rate/README.rst
odoo/addons/account_invoice_show_currency_rate/__init__.py
odoo/addons/account_invoice_show_currency_rate/__manifest__.py
odoo/addons/account_invoice_show_currency_rate/i18n/account_invoice_show_currency_rate.pot
odoo/addons/account_invoice_show_currency_rate/i18n/es.po
odoo/addons/account_invoice_show_currency_rate/models/__init__.py
odoo/addons/account_invoice_show_currency_rate/models/account_move.py
odoo/addons/account_invoice_show_currency_rate/readme/CONFIGURE.rst
odoo/addons/account_invoice_show_currency_rate/readme/CONTRIBUTORS.rst
odoo/addons/account_invoice_show_currency_rate/readme/DESCRIPTION.rst
odoo/addons/account_invoice_show_currency_rate/readme/USAGE.rst
odoo/addons/account_invoice_show_currency_rate/static/description/icon.png
odoo/addons/account_invoice_show_currency_rate/static/description/index.html
odoo/addons/account_invoice_show_currency_rate/tests/__init__.py
odoo/addons/account_invoice_show_currency_rate/tests/test_account_move.py
odoo/addons/account_invoice_show_currency_rate/views/account_move_view.xml
odoo13_addon_account_invoice_show_currency_rate-13.0.1.1.0.dist-info/METADATA
odoo13_addon_account_invoice_show_currency_rate-13.0.1.1.0.dist-info/WHEEL
odoo13_addon_account_invoice_show_currency_rate-13.0.1.1.0.dist-info/top_level.txt
odoo13_addon_account_invoice_show_currency_rate-13.0.1.1.0.dist-info/RECORD
